easepy/__init__.py
easepy/ease_grid.py
easepy-1.1.2.dist-info/LICENSE
easepy-1.1.2.dist-info/WHEEL
easepy-1.1.2.dist-info/METADATA
easepy-1.1.2.dist-info/RECORD
